gargoyle/__init__.py
gargoyle/admin.py
gargoyle/builtins.py
gargoyle/conditions.py
gargoyle/decorators.py
gargoyle/helpers.py
gargoyle/manager.py
gargoyle/models.py
gargoyle/nexus_modules.py
gargoyle/proxy.py
gargoyle/signals.py
gargoyle/testutils.py
gargoyle/management/__init__.py
gargoyle/management/commands/__init__.py
gargoyle/management/commands/add_switch.py
gargoyle/management/commands/remove_switch.py
gargoyle/media/css/gargoyle.css
gargoyle/media/img/button-bg.jpg
gargoyle/media/img/delete.png
gargoyle/media/img/edit.png
gargoyle/media/js/gargoyle.js
gargoyle/media/js/string_score.min.js
gargoyle/migrations/0001_initial.py
gargoyle/migrations/0002_auto__add_field_switch_date_modified.py
gargoyle/migrations/0003_auto__chg_field_switch_label__chg_field_switch_key.py
gargoyle/migrations/__init__.py
gargoyle/templates/gargoyle/index.html
gargoyle/templates/gargoyle/nexus/dashboard.html
gargoyle/templatetags/__init__.py
gargoyle/templatetags/gargoyle_helpers.py
gargoyle/templatetags/gargoyle_tags.py
gargoyle-0.11.0.dist-info/DESCRIPTION.rst
gargoyle-0.11.0.dist-info/METADATA
gargoyle-0.11.0.dist-info/metadata.json
gargoyle-0.11.0.dist-info/RECORD
gargoyle-0.11.0.dist-info/top_level.txt
gargoyle-0.11.0.dist-info/WHEEL
